hanapin/__init__.py
hanapin/ask.py
hanapin/bing.py
hanapin/ddg.py
hanapin/google.py
hanapin/lib.py
tests/__init__.py
tests/test_search.py
hanapin-0.1.6.dist-info/LICENSE
hanapin-0.1.6.dist-info/METADATA
hanapin-0.1.6.dist-info/WHEEL
hanapin-0.1.6.dist-info/top_level.txt
hanapin-0.1.6.dist-info/RECORD
