Metadata-Version: 2.1
Name: hanapin
Version: 0.1.6
Summary: Simple web search library
Home-page: https://github.com/TheBoringDude/hanapin
Author: TheBoringDude
Author-email: iamcoderx@gmail.com
License: MIT
Project-URL: Bug Tracker, https://github.com/TheBoringDude/hanapin/issues
Platform: UNKNOWN
Classifier: License :: OSI Approved :: MIT License
Classifier: Programming Language :: Python :: 3
Classifier: Programming Language :: Python :: 3.6
Classifier: Programming Language :: Python :: 3.7
Classifier: Programming Language :: Python :: 3.8
Requires-Dist: requests
Requires-Dist: bs4
Requires-Dist: lxml
